django_namespace/__init__.py
django_namespaces/__init__.py
django_namespaces/admin.py
django_namespaces/apps.py
django_namespaces/blocked.py
django_namespaces/conf.py
django_namespaces/context_processors.py
django_namespaces/import_utils.py
django_namespaces/middleware.py
django_namespaces/models.py
django_namespaces/namespaces.py
django_namespaces/tests.py
django_namespaces/validators.py
django_namespaces/migrations/0001_initial.py
django_namespaces/migrations/__init__.py
django_namespace-0.0.1.dist-info/METADATA
django_namespace-0.0.1.dist-info/WHEEL
django_namespace-0.0.1.dist-info/top_level.txt
django_namespace-0.0.1.dist-info/RECORD
