Metadata-Version: 2.1
Name: django-namespace
Version: 0.0.1
Summary: UNKNOWN
Home-page: https://github.com/jmitchel3/django-namespace
Author: Justin Mitchel
Author-email: hello@teamcfe.com
License: MIT
Project-URL: Documentation, https://github.com/jmitchel3/django-namespace
Project-URL: Changelog, https://github.com/jmitchel3/django-namespace/blob/main/HISTORY.rst
Project-URL: Twitter, https://twitter.com/joincfe
Keywords: Django
Platform: UNKNOWN
Classifier: Development Status :: 7 - Inactive
Classifier: Framework :: Django :: 3.2
Classifier: Framework :: Django :: 4.0
Classifier: Framework :: Django :: 4.1
Classifier: Intended Audience :: Developers
Classifier: License :: OSI Approved :: MIT License
Classifier: Natural Language :: English
Classifier: Operating System :: OS Independent
Classifier: Programming Language :: Python :: 3 :: Only
Classifier: Programming Language :: Python :: 3
Classifier: Programming Language :: Python :: 3.7
Classifier: Programming Language :: Python :: 3.8
Classifier: Programming Language :: Python :: 3.9
Classifier: Programming Language :: Python :: 3.10
Classifier: Programming Language :: Python :: 3.11
Classifier: Typing :: Typed
Requires-Python: >=3.7
Requires-Dist: Django (>=3.2)
